Workbook

Sheet INDEX
A1: DGS — INDEX DES DOCUMENTS
A2: EURL DYNAMIC GROUP SOLUTION · Code : DGS-SYS-003 · Version : V1.0 · Date : 19/09/2026 · Statut : BROUILLON
A4: Code | B4: Document | C4: Catégorie | D4: Utilisation | E4: Signature | F4: Version | G4: Dossier | H4: Lot | I4: Statut de création | J4: Statut du document | K4: Fichier
A5: DGS-CLI-001 | B5: Fiche d’identification client | C5: Client — Identification | D5: Identifier le client (personne physique ou morale) et ouvrir son dossier | E5: Client + DGS | F5: V1.0 | G5: 02_CLIENTS/Identification | H5: 1 | I5: Créé | J5: BROUILLON | K5: DGS-CLI-001-Fiche-Identification-Client.docx
A6: DGS-CLI-002 | B6: Fiche de demande client | C6: Client — Identification | D6: Enregistrer la demande initiale, le besoin exprimé et le budget indicatif | E6: DGS (+ Client) | F6: V1.0 | G6: 02_CLIENTS/Identification | H6: 2B | I6: Créé | J6: BROUILLON | K6: DGS-CLI-002-Fiche-Demande-Client.docx
A7: DGS-CLI-003 | B7: Fiche de visite | C7: Client — Identification | D7: Consigner les observations techniques de la visite de site | E7: DGS (+ Client) | F7: V1.0 | G7: 02_CLIENTS/Identification | H7: 2B | I7: Créé | J7: BROUILLON | K7: DGS-CLI-003-Fiche-Visite.docx
A8: DGS-CLI-004 | B8: Fiche de relevé | C8: Client — Identification | D8: Consigner les relevés dimensionnels pièce par pièce | E8: DGS | F8: V1.0 | G8: 02_CLIENTS/Identification | H8: 2B | I8: Créé | J8: BROUILLON | K8: DGS-CLI-004-Fiche-Releve.docx
A9: DGS-CLI-005 | B9: Cahier des besoins client | C9: Client — Identification | D9: Formaliser programme, attentes, contraintes et priorités du client | E9: Client + DGS | F9: V1.0 | G9: 02_CLIENTS/Identification | H9: 2B | I9: Créé | J9: BROUILLON | K9: DGS-CLI-005-Cahier-Besoins-Client.docx
A10: DGS-CLI-006 | B10: Compte rendu de réunion client | C10: Client — Identification | D10: Tracer les échanges et décisions d’une réunion avec le client | E10: DGS (+ Client) | F10: V1.0 | G10: 02_CLIENTS/Identification | H10: 2B | I10: Créé | J10: BROUILLON | K10: DGS-CLI-006-Compte-Rendu-Reunion-Client.docx
A11: DGS-CLI-007 | B11: Devis estimatif | C11: Client — Devis et offres | D11: Donner une évaluation budgétaire indicative avant le devis détaillé | E11: DGS (+ Client) | F11: V1.0 | G11: 02_CLIENTS/Devis_Offres | H11: 1 | I11: Créé | J11: BROUILLON | K11: DGS-CLI-007-Devis-Estimatif.docx
A12: DGS-CLI-008 | B12: Devis détaillé | C12: Client — Devis et offres | D12: Chiffrer les travaux par lot (quantités, prix unitaires, totaux) | E12: DGS + Client | F12: V1.0 | G12: 02_CLIENTS/Devis_Offres | H12: 1 | I12: Créé | J12: BROUILLON | K12: DGS-CLI-008-Devis-Detaille.docx
A13: DGS-CLI-009 | B13: Offre commerciale | C13: Client — Devis et offres | D13: Présenter l’offre complète : méthode, planning, prix, conditions | E13: DGS + Client | F13: V1.0 | G13: 02_CLIENTS/Devis_Offres | H13: 1 | I13: Créé | J13: BROUILLON | K13: DGS-CLI-009-Offre-Commerciale.docx
A14: DGS-CLI-010 | B14: Bordereau des prix | C14: Client — Devis et offres | D14: Lister les prix unitaires applicables aux prestations | E14: DGS (+ Client) | F14: V1.0 | G14: 02_CLIENTS/Devis_Offres | H14: 2B | I14: Créé | J14: BROUILLON | K14: DGS-CLI-010-Bordereau-Prix.docx
A15: DGS-CLI-011 | B15: Conditions de paiement | C15: Client — Devis et offres | D15: Définir échéancier, acomptes et modalités de règlement | E15: DGS + Client | F15: V1.0 | G15: 02_CLIENTS/Devis_Offres | H15: 2B | I15: Créé | J15: BROUILLON | K15: DGS-CLI-011-Conditions-Paiement.docx
... A283: DGS-SYS-006 | B283: Catalogue des champs variables (BLACKREBEL) | C283: Système documentaire | D283: Lister, document par document, les champs remplissables automatiquement et leur clé | E283: Aucune (référentiel technique) | F283: V1.0 | G283: 00_README | H283: 13 | I283: Créé | J283: BROUILLON | K283: DGS-SYS-006-Catalogue-Champs-BLACKREBEL.xlsx

Sheet SYNTHÈSE
A1: SYNTHÈSE — avancement de la création
A2: Les chiffres se recalculent automatiquement à partir de la feuille INDEX (colonnes Lot et Statut de création).
A4: Lot | B4: Contenu | C4: Documents | D4: Créés | E4: À créer
A5: 1 | B5: Master Template, README, Index, Rapport, Fiche client, Fiche projet, Devis, Offre commerciale, Bon pour accord | C5: =COUNTIF(INDEX!$H$5:$H$283,A5) | D5: =COUNTIFS(INDEX!$H$5:$H$283,A5,INDEX!$I$5:$I$283,"Créé") | E5: =COUNTIFS(INDEX!$H$5:$H$283,A5,INDEX!$I$5:$I$283,"À créer")
A6: 2 | B6: Contrat général de travaux, rénovation, finition, clé en main, avenant | C6: =COUNTIF(INDEX!$H$5:$H$283,A6) | D6: =COUNTIFS(INDEX!$H$5:$H$283,A6,INDEX!$I$5:$I$283,"Créé") | E6: =COUNTIFS(INDEX!$H$5:$H$283,A6,INDEX!$I$5:$I$283,"À créer")
A7: 2B | B7: Autres contrats et documents client (fiches, cahier des besoins, bordereau, conditions de paiement) | C7: =COUNTIF(INDEX!$H$5:$H$283,A7) | D7: =COUNTIFS(INDEX!$H$5:$H$283,A7,INDEX!$I$5:$I$283,"Créé") | E7: =COUNTIFS(INDEX!$H$5:$H$283,A7,INDEX!$I$5:$I$283,"À créer")
A8: 3 | B8: PV client, SAV / garantie, choix des matériaux | C8: =COUNTIF(INDEX!$H$5:$H$283,A8) | D8: =COUNTIFS(INDEX!$H$5:$H$283,A8,INDEX!$I$5:$I$283,"Créé") | E8: =COUNTIFS(INDEX!$H$5:$H$283,A8,INDEX!$I$5:$I$283,"À créer")
A9: 4 | B9: PV chantier, qualité, HSE, matériaux | C9: =COUNTIF(INDEX!$H$5:$H$283,A9) | D9: =COUNTIFS(INDEX!$H$5:$H$283,A9,INDEX!$I$5:$I$283,"Créé") | E9: =COUNTIFS(INDEX!$H$5:$H$283,A9,INDEX!$I$5:$I$283,"À créer")
A10: 5 | B10: Fournisseurs et sous-traitants | C10: =COUNTIF(INDEX!$H$5:$H$283,A10) | D10: =COUNTIFS(INDEX!$H$5:$H$283,A10,INDEX!$I$5:$I$283,"Créé") | E10: =COUNTIFS(INDEX!$H$5:$H$283,A10,INDEX!$I$5:$I$283,"À créer")
A11: 6 | B11: Personnel, matériel et véhicules | C11: =COUNTIF(INDEX!$H$5:$H$283,A11) | D11: =COUNTIFS(INDEX!$H$5:$H$283,A11,INDEX!$I$5:$I$283,"Créé") | E11: =COUNTIFS(INDEX!$H$5:$H$283,A11,INDEX!$I$5:$I$283,"À créer")
A12: 7 | B12: Administration EURL (décisions de l’associé unique) | C12: =COUNTIF(INDEX!$H$5:$H$283,A12) | D12: =COUNTIFS(INDEX!$H$5:$H$283,A12,INDEX!$I$5:$I$283,"Créé") | E12: =COUNTIFS(INDEX!$H$5:$H$283,A12,INDEX!$I$5:$I$283,"À créer")
A13: 8 | B13: Promotion immobilière | C13: =COUNTIF(INDEX!$H$5:$H$283,A13) | D13: =COUNTIFS(INDEX!$H$5:$H$283,A13,INDEX!$I$5:$I$283,"Créé") | E13: =COUNTIFS(INDEX!$H$5:$H$283,A13,INDEX!$I$5:$I$283,"À créer")
A14: 9 | B14: Ressources humaines : contrats de travail, attestation, congés, fiche de poste, règlement intérieur, ordre de mission, solde de tout compte | C14: =COUNTIF(INDEX!$H$5:$H$283,A14) | D14: =COUNTIFS(INDEX!$H$5:$H$283,A14,INDEX!$I$5:$I$283,"Créé") | E14: =COUNTIFS(INDEX!$H$5:$H$283,A14,INDEX!$I$5:$I$283,"À créer")
A15: 10 | B15: Correspondance et relation client : reçu, rappel, mise en demeure, réclamation, révision, transmission, attestation, résiliation, satisfaction, annulation | C15: =COUNTIF(INDEX!$H$5:$H$283,A15) | D15: =COUNTIFS(INDEX!$H$5:$H$283,A15,INDEX!$I$5:$I$283,"Créé") | E15: =COUNTIFS(INDEX!$H$5:$H$283,A15,INDEX!$I$5:$I$283,"À créer")
A16: 11 | B16: Suivi de chantier : journal, rapports, pointage, attachement, ordre de service, planning, approvisionnement, registre des non-conformités, sécurité quotidienne | C16: =COUNTIF(INDEX!$H$5:$H$283,A16) | D16: =COUNTIFS(INDEX!$H$5:$H$283,A16,INDEX!$I$5:$I$283,"Créé") | E16: =COUNTIFS(INDEX!$H$5:$H$283,A16,INDEX!$I$5:$I$283,"À créer")
... A19: 14 | B19: Marchés publics — compléments et réorganisation par usage : 55 documents (analyse du cahier des charges, déclarations, capacités, dépôt, résultats, procédures simplifiées, attribution, exécution, clôture) et classement du dossier 10_MARCHES_PUBLICS en 15 dossiers | C19: =COUNTIF(INDEX!$H$5:$H$283,A19) | D19: =COUNTIFS(INDEX!$H$5:$H$283,A19,INDEX!$I$5:$I$283,"Créé") | E19: =COUNTIFS(INDEX!$H$5:$H$283,A19,INDEX!$I$5:$I$283,"À créer")
A20: TOTAL | C20: =SUM(C5:C19) | D20: =SUM(D5:D19) | E20: =SUM(E5:E19)
A21: Contrôle : le total doit égaler le nombre de lignes de INDEX | C21: =IF(C20=COUNTA(INDEX!$A$5:$A$283),"OK","ÉCART")
A24: Famille | B24: Libellé | C24: Documents | D24: Créés | E24: À créer
A25: DGS-CON-* | B25: Contrats | C25: =SUMPRODUCT(--(LEFT(INDEX!$A$5:$A$283,8)="DGS-CON-")) | D25: =SUMPRODUCT(--(LEFT(INDEX!$A$5:$A$283,8)="DGS-CON-"),--(INDEX!$I$5:$I$283="Créé")) | E25: =C25-D25
A26: DGS-PV-* | B26: Procès-verbaux clients | C26: =SUMPRODUCT(--(LEFT(INDEX!$A$5:$A$283,7)="DGS-PV-")) | D26: =SUMPRODUCT(--(LEFT(INDEX!$A$5:$A$283,7)="DGS-PV-"),--(INDEX!$I$5:$I$283="Créé")) | E26: =C26-D26
A27: DGS-CLI-* | B27: Documents clients | C27: =SUMPRODUCT(--(LEFT(INDEX!$A$5:$A$283,8)="DGS-CLI-")) | D27: =SUMPRODUCT(--(LEFT(INDEX!$A$5:$A$283,8)="DGS-CLI-"),--(INDEX!$I$5:$I$283="Créé")) | E27: =C27-D27
A28: DGS-CHT-* | B28: Chantiers | C28: =SUMPRODUCT(--(LEFT(INDEX!$A$5:$A$283,8)="DGS-CHT-")) | D28: =SUMPRODUCT(--(LEFT(INDEX!$A$5:$A$283,8)="DGS-CHT-"),--(INDEX!$I$5:$I$283="Créé")) | E28: =C28-D28
A29: DGS-FOU-* | B29: Fournisseurs | C29: =SUMPRODUCT(--(LEFT(INDEX!$A$5:$A$283,8)="DGS-FOU-")) | D29: =SUMPRODUCT(--(LEFT(INDEX!$A$5:$A$283,8)="DGS-FOU-"),--(INDEX!$I$5:$I$283="Créé")) | E29: =C29-D29
A30: DGS-ST-* | B30: Sous-traitants | C30: =SUMPRODUCT(--(LEFT(INDEX!$A$5:$A$283,7)="DGS-ST-")) | D30: =SUMPRODUCT(--(LEFT(INDEX!$A$5:$A$283,7)="DGS-ST-"),--(INDEX!$I$5:$I$283="Créé")) | E30: =C30-D30
A31: DGS-HSE-* | B31: Hygiène, sécurité, environnement | C31: =SUMPRODUCT(--(LEFT(INDEX!$A$5:$A$283,8)="DGS-HSE-")) | D31: =SUMPRODUCT(--(LEFT(INDEX!$A$5:$A$283,8)="DGS-HSE-"),--(INDEX!$I$5:$I$283="Créé")) | E31: =C31-D31
A32: DGS-QLT-* | B32: Qualité | C32: =SUMPRODUCT(--(LEFT(INDEX!$A$5:$A$283,8)="DGS-QLT-")) | D32: =SUMPRODUCT(--(LEFT(INDEX!$A$5:$A$283,8)="DGS-QLT-"),--(INDEX!$I$5:$I$283="Créé")) | E32: =C32-D32
A33: DGS-FIN-* | B33: Finance | C33: =SUMPRODUCT(--(LEFT(INDEX!$A$5:$A$283,8)="DGS-FIN-")) | D33: =SUMPRODUCT(--(LEFT(INDEX!$A$5:$A$283,8)="DGS-FIN-"),--(INDEX!$I$5:$I$283="Créé")) | E33: =C33-D33
A34: DGS-ADM-* | B34: Administration | C34: =SUMPRODUCT(--(LEFT(INDEX!$A$5:$A$283,8)="DGS-ADM-")) | D34: =SUMPRODUCT(--(LEFT(INDEX!$A$5:$A$283,8)="DGS-ADM-"),--(INDEX!$I$5:$I$283="Créé")) | E34: =C34-D34
A35: DGS-PER-* | B35: Personnel (extension) | C35: =SUMPRODUCT(--(LEFT(INDEX!$A$5:$A$283,8)="DGS-PER-")) | D35: =SUMPRODUCT(--(LEFT(INDEX!$A$5:$A$283,8)="DGS-PER-"),--(INDEX!$I$5:$I$283="Créé")) | E35: =C35-D35
A36: DGS-MAT-* | B36: Matériel et véhicules (extension) | C36: =SUMPRODUCT(--(LEFT(INDEX!$A$5:$A$283,8)="DGS-MAT-")) | D36: =SUMPRODUCT(--(LEFT(INDEX!$A$5:$A$283,8)="DGS-MAT-"),--(INDEX!$I$5:$I$283="Créé")) | E36: =C36-D36
A37: DGS-PRO-* | B37: Promotion immobilière (extension) | C37: =SUMPRODUCT(--(LEFT(INDEX!$A$5:$A$283,8)="DGS-PRO-")) | D37: =SUMPRODUCT(--(LEFT(INDEX!$A$5:$A$283,8)="DGS-PRO-"),--(INDEX!$I$5:$I$283="Créé")) | E37: =C37-D37
A38: DGS-MAR-* | B38: Marchés publics (extension) | C38: =SUMPRODUCT(--(LEFT(INDEX!$A$5:$A$283,8)="DGS-MAR-")) | D38: =SUMPRODUCT(--(LEFT(INDEX!$A$5:$A$283,8)="DGS-MAR-"),--(INDEX!$I$5:$I$283="Créé")) | E38: =C38-D38
A39: DGS-SYS-* | B39: Système documentaire (extension) | C39: =SUMPRODUCT(--(LEFT(INDEX!$A$5:$A$283,8)="DGS-SYS-")) | D39: =SUMPRODUCT(--(LEFT(INDEX!$A$5:$A$283,8)="DGS-SYS-"),--(INDEX!$I$5:$I$283="Créé")) | E39: =C39-D39
A42: LÉGENDE — cellules à modifier
A43: INDEX, colonne « Statut de création » : passer de « À créer » à « Créé » lorsque le fichier est produit.
A44: INDEX, colonne « Statut du document » : BROUILLON, VALIDÉ ou OBSOLÈTE selon la procédure du README.
A45: INDEX, colonne « Version » : mettre à jour à chaque nouvelle version (V1.1, V2.0…).
A46: Les lignes sur fond doré clair sont les documents déjà créés (lots 1 et 2). Exemple de ligne : DGS-CLI-001 · Fiche d’identification client · V1.0 · Créé · BROUILLON.

Sheet CORRESPONDANCES
A1: CORRESPONDANCES — intitulés de la liste initiale regroupés sous un code unique
A3: N° liste | B3: Intitulé demandé | C3: Code retenu | D3: Motif
A4: 61 | B4: PV de validation d’échantillon | C4: DGS-PV-008 | D4: Identique au PV de validation des échantillons (n° 30)
A5: 65 | B5: PV de non-conformité fournisseur | C5: DGS-FOU-007 | D5: Identique au PV non-conformité fournisseur (n° 91)
A6: 67 | B6: PV de réunion de chantier | C6: DGS-PV-010 | D6: Identique au PV de réunion de chantier (n° 32)
A7: 83 | B7: PV de suspension | C7: DGS-PV-017 | D7: Identique au PV de suspension des travaux (n° 39)
A8: 84 | B8: PV de reprise | C8: DGS-PV-018 | D8: Identique au PV de reprise des travaux (n° 40)
A9: 107 | B9: PV restitution véhicule | C9: DGS-MAT-005 | D9: Identique au PV restitution véhicule (n° 115)
